laser_mind_client/__init__.py
laser_mind_client/laser_mind_client.py
laser_mind_client-0.55.0.dist-info/licenses/LICENSE
laser_mind_client-0.55.0.dist-info/METADATA
laser_mind_client-0.55.0.dist-info/WHEEL
laser_mind_client-0.55.0.dist-info/top_level.txt
laser_mind_client-0.55.0.dist-info/RECORD
